reghub_pack/Dataset.py
reghub_pack/__init__.py
reghub_pack/general_functions.py
reghub_pack/models/BERT.py
reghub_pack/models/BERT_similarity.py
reghub_pack/models/LLaMA.py
reghub_pack/models/RoBERTa.py
reghub_pack/models/__init__.py
reghub_pack/models/spacy_NER.py
reghub_pack/module1.py
reghub_pack/tokenizer.py
reghub_pack-0.1.6.dist-info/LICENSE
reghub_pack-0.1.6.dist-info/METADATA
reghub_pack-0.1.6.dist-info/WHEEL
reghub_pack-0.1.6.dist-info/RECORD
