Metadata-Version: 2.1
Name: reghub-pack
Version: 0.1.6
Summary: 
License: MIT
Author: Kirtesh, Nils, Xiang
Requires-Python: >=3.9,<4.0
Classifier: License :: OSI Approved :: MIT License
Classifier: Programming Language :: Python :: 3
Classifier: Programming Language :: Python :: 3.9
Classifier: Programming Language :: Python :: 3.10
Classifier: Programming Language :: Python :: 3.11
Classifier: Programming Language :: Python :: 3.12
